pynenv/__init__.py
pynenv/environment.py
pynenv-0.2.6.dist-info/LICENSE
pynenv-0.2.6.dist-info/METADATA
pynenv-0.2.6.dist-info/WHEEL
pynenv-0.2.6.dist-info/RECORD
