Metadata-Version: 2.1
Name: pynenv
Version: 0.2.6
Summary: General helper functions for environments
Author: Nik Sheridan
Author-email: niksheridan@duck.com
Requires-Python: >=3.12,<4.0
Classifier: Programming Language :: Python :: 3
Classifier: Programming Language :: Python :: 3.12
Requires-Dist: loguru (>=0.7.2,<0.8.0)
Requires-Dist: pyaml (>=24.4.0,<25.0.0)
Requires-Dist: pyjson (>=1.4.1,<2.0.0)
